backseat_driver/__init__.py
backseat_driver/backseat_driver.py
backseat_driver-0.0.2.dist-info/LICENSE
backseat_driver-0.0.2.dist-info/METADATA
backseat_driver-0.0.2.dist-info/WHEEL
backseat_driver-0.0.2.dist-info/entry_points.txt
backseat_driver-0.0.2.dist-info/top_level.txt
backseat_driver-0.0.2.dist-info/RECORD
