Metadata-Version: 2.1
Name: backseat-driver
Version: 0.0.2
Summary: A tool for large language model-enabled code review.
Home-page: https://github.com/kostaleonard/backseat-driver
Author: Leo Kosta
Author-email: kostaleonard@gmail.com
Project-URL: Bug Tracker, https://github.com/kostaleonard/backseat-driver/issues
Classifier: Programming Language :: Python :: 3
Classifier: License :: OSI Approved :: MIT License
Classifier: Operating System :: OS Independent
License-File: LICENSE
Requires-Dist: openai
